drf_base/__init__.py
drf_base/mixins.py
drf_base/pagination.py
drf_base/permissions.py
drf_base/serializers.py
drf_base/utils.py
drf_base/viewsets.py
drf_base-0.1.0.dist-info/METADATA
drf_base-0.1.0.dist-info/WHEEL
drf_base-0.1.0.dist-info/top_level.txt
drf_base-0.1.0.dist-info/RECORD
