Metadata-Version: 2.4
Name: drf-base
Version: 0.1.0
Summary: A thin wrapper for Django REST Framework
Author-email: Your Name <your.email@example.com>
License: MIT
Requires-Dist: Django<5.0,>=4.2
Requires-Dist: djangorestframework<3.16,>=3.15
Provides-Extra: filter
Requires-Dist: django-filter<25,>=24; extra == "filter"
